[{"year_id": 2015100000.0, "year": "2015年度", "area_id": 13101.0, "area": "東京都 千代田区", "desc": null, "jinkou": 58406.0, "jinkou_desc": null, "otoko": 29343.0, "otoko_desc": null, "onna": 29063.0, "onna_desc": null}, {"year_id": 2015100000.0, "year": "2015年度", "area_id": 13102.0, "area": "東京都 中央区", "desc": null, "jinkou": 141183.0, "jinkou_desc": null, "otoko": 67536.0, "otoko_desc": null, "onna": 73647.0, "onna_desc": null}, {"year_id": 2015100000.0, "year": "2015年度", "area_id": 13103.0, "area": "東京都 港区", "desc": null, "jinkou": 243283.0, "jinkou_desc": null, "otoko": 114717.0, "otoko_desc": null, "onna": 128566.0, "onna_desc": null}, {"year_id": 2015100000.0, "year": "2015年度", "area_id": 13104.0, "area": "東京都 新宿区", "desc": null, "jinkou": 333560.0, "jinkou_desc": null, "otoko": 167258.0, "otoko_desc": null, "onna": 166302.0, "onna_desc": null}, {"year_id": 2015100000.0, "year": "2015年度", "area_id": 13105.0, "area": "東京都 文京区", "desc": null, "jinkou": 219724.0, "jinkou_desc": null, "otoko": 105990.0, "otoko_desc": null, "onna": 113734.0, "onna_desc": null}, {"year_id": 2015100000.0, "year": "2015年度", "area_id": 13106.0, "area": "東京都 台東区", "desc": null, "jinkou": 198073.0, "jinkou_desc": null, "otoko": 101982.0, "otoko_desc": null, "onna": 96091.0, "onna_desc": null}, {"year_id": 2015100000.0, "year": "2015年度", "area_id": 13107.0, "area": "東京都 墨田区", "desc": null, "jinkou": 256274.0, "jinkou_desc": null, "otoko": 127925.0, "otoko_desc": null, "onna": 128349.0, "onna_desc": null}, {"year_id": 2015100000.0, "year": "2015年度", "area_id": 13108.0, "area": "東京都 江東区", "desc": null, "jinkou": 498109.0, "jinkou_desc": null, "otoko": 246750.0, "otoko_desc": null, "onna": 251359.0, "onna_desc": null}, {"year_id": 2015100000.0, "year": "2015年度", "area_id": 13109.0, "area": "東京都 品川区", "desc": null, "jinkou": 386855.0, "jinkou_desc": null, "otoko": 191090.0, "otoko_desc": null, "onna": 195765.0, "onna_desc": null}, {"year_id": 2015100000.0, "year": "2015年度", "area_id": 13110.0, "area": "東京都 目黒区", "desc": null, "jinkou": 277622.0, "jinkou_desc": null, "otoko": 130947.0, "otoko_desc": null, "onna": 146675.0, "onna_desc": null}, {"year_id": 2015100000.0, "year": "2015年度", "area_id": 13111.0, "area": "東京都 大田区", "desc": null, "jinkou": 717082.0, "jinkou_desc": null, "otoko": 359753.0, "otoko_desc": null, "onna": 357329.0, "onna_desc": null}, {"year_id": 2015100000.0, "year": "2015年度", "area_id": 13112.0, "area": "東京都 世田谷区", "desc": null, "jinkou": 903346.0, "jinkou_desc": null, "otoko": 428874.0, "otoko_desc": null, "onna": 474472.0, "onna_desc": null}, {"year_id": 2015100000.0, "year": "2015年度", "area_id": 13113.0, "area": "東京都 渋谷区", "desc": null, "jinkou": 224533.0, "jinkou_desc": null, "otoko": 107986.0, "otoko_desc": null, "onna": 116547.0, "onna_desc": null}, {"year_id": 2015100000.0, "year": "2015年度", "area_id": 13114.0, "area": "東京都 中野区", "desc": null, "jinkou": 328215.0, "jinkou_desc": null, "otoko": 165382.0, "otoko_desc": null, "onna": 162833.0, "onna_desc": null}, {"year_id": 2015100000.0, "year": "2015年度", "area_id": 13115.0, "area": "東京都 杉並区", "desc": null, "jinkou": 563997.0, "jinkou_desc": null, "otoko": 271737.0, "otoko_desc": null, "onna": 292260.0, "onna_desc": null}, {"year_id": 2015100000.0, "year": "2015年度", "area_id": 13116.0, "area": "東京都 豊島区", "desc": null, "jinkou": 291167.0, "jinkou_desc": null, "otoko": 146827.0, "otoko_desc": null, "onna": 144340.0, "onna_desc": null}, {"year_id": 2015100000.0, "year": "2015年度", "area_id": 13117.0, "area": "東京都 北区", "desc": null, "jinkou": 341076.0, "jinkou_desc": null, "otoko": 169829.0, "otoko_desc": null, "onna": 171247.0, "onna_desc": null}, {"year_id": 2015100000.0, "year": "2015年度", "area_id": 13118.0, "area": "東京都 荒川区", "desc": null, "jinkou": 212264.0, "jinkou_desc": null, "otoko": 105113.0, "otoko_desc": null, "onna": 107151.0, "onna_desc": null}, {"year_id": 2015100000.0, "year": "2015年度", "area_id": 13119.0, "area": "東京都 板橋区", "desc": null, "jinkou": 561916.0, "jinkou_desc": null, "otoko": 276592.0, "otoko_desc": null, "onna": 285324.0, "onna_desc": null}, {"year_id": 2015100000.0, "year": "2015年度", "area_id": 13120.0, "area": "東京都 練馬区", "desc": null, "jinkou": 721722.0, "jinkou_desc": null, "otoko": 351609.0, "otoko_desc": null, "onna": 370113.0, "onna_desc": null}, {"year_id": 2015100000.0, "year": "2015年度", "area_id": 13121.0, "area": "東京都 足立区", "desc": null, "jinkou": 670122.0, "jinkou_desc": null, "otoko": 334922.0, "otoko_desc": null, "onna": 335200.0, "onna_desc": null}, {"year_id": 2015100000.0, "year": "2015年度", "area_id": 13122.0, "area": "東京都 葛飾区", "desc": null, "jinkou": 442913.0, "jinkou_desc": null, "otoko": 221621.0, "otoko_desc": null, "onna": 221292.0, "onna_desc": null}, {"year_id": 2015100000.0, "year": "2015年度", "area_id": 13123.0, "area": "東京都 江戸川区", "desc": null, "jinkou": 681298.0, "jinkou_desc": null, "otoko": 343464.0, "otoko_desc": null, "onna": 337834.0, "onna_desc": null}, {"year_id": 2015100000.0, "year": "2015年度", "area_id": 13201.0, "area": "東京都 八王子市", "desc": null, "jinkou": 577513.0, "jinkou_desc": null, "otoko": 291238.0, "otoko_desc": null, "onna": 286275.0, "onna_desc": null}, {"year_id": 2015100000.0, "year": "2015年度", "area_id": 13202.0, "area": "東京都 立川市", "desc": null, "jinkou": 176295.0, "jinkou_desc": null, "otoko": 86978.0, "otoko_desc": null, "onna": 89317.0, "onna_desc": null}, {"year_id": 2015100000.0, "year": "2015年度", "area_id": 13203.0, "area": "東京都 武蔵野市", "desc": null, "jinkou": 144730.0, "jinkou_desc": null, "otoko": 69475.0, "otoko_desc": null, "onna": 75255.0, "onna_desc": null}, {"year_id": 2015100000.0, "year": "2015年度", "area_id": 13204.0, "area": "東京都 三鷹市", "desc": null, "jinkou": 186936.0, "jinkou_desc": null, "otoko": 90641.0, "otoko_desc": null, "onna": 96295.0, "onna_desc": null}, {"year_id": 2015100000.0, "year": "2015年度", "area_id": 13205.0, "area": "東京都 青梅市", "desc": null, "jinkou": 137381.0, "jinkou_desc": null, "otoko": 68677.0, "otoko_desc": null, "onna": 68704.0, "onna_desc": null}, {"year_id": 2015100000.0, "year": "2015年度", "area_id": 13206.0, "area": "東京都 府中市", "desc": null, "jinkou": 260274.0, "jinkou_desc": null, "otoko": 132172.0, "otoko_desc": null, "onna": 128102.0, "onna_desc": null}, {"year_id": 2015100000.0, "year": "2015年度", "area_id": 13207.0, "area": "東京都 昭島市", "desc": null, "jinkou": 111539.0, "jinkou_desc": null, "otoko": 55394.0, "otoko_desc": null, "onna": 56145.0, "onna_desc": null}, {"year_id": 2015100000.0, "year": "2015年度", "area_id": 13208.0, "area": "東京都 調布市", "desc": null, "jinkou": 229061.0, "jinkou_desc": null, "otoko": 111921.0, "otoko_desc": null, "onna": 117140.0, "onna_desc": null}, {"year_id": 2015100000.0, "year": "2015年度", "area_id": 13209.0, "area": "東京都 町田市", "desc": null, "jinkou": 432348.0, "jinkou_desc": null, "otoko": 212312.0, "otoko_desc": null, "onna": 220036.0, "onna_desc": null}, {"year_id": 2015100000.0, "year": "2015年度", "area_id": 13210.0, "area": "東京都 小金井市", "desc": null, "jinkou": 121396.0, "jinkou_desc": null, "otoko": 60168.0, "otoko_desc": null, "onna": 61228.0, "onna_desc": null}, {"year_id": 2015100000.0, "year": "2015年度", "area_id": 13211.0, "area": "東京都 小平市", "desc": null, "jinkou": 190005.0, "jinkou_desc": null, "otoko": 93777.0, "otoko_desc": null, "onna": 96228.0, "onna_desc": null}, {"year_id": 2015100000.0, "year": "2015年度", "area_id": 13212.0, "area": "東京都 日野市", "desc": null, "jinkou": 186283.0, "jinkou_desc": null, "otoko": 93349.0, "otoko_desc": null, "onna": 92934.0, "onna_desc": null}, {"year_id": 2015100000.0, "year": "2015年度", "area_id": 13213.0, "area": "東京都 東村山市", "desc": null, "jinkou": 149956.0, "jinkou_desc": null, "otoko": 73314.0, "otoko_desc": null, "onna": 76642.0, "onna_desc": null}, {"year_id": 2015100000.0, "year": "2015年度", "area_id": 13214.0, "area": "東京都 国分寺市", "desc": null, "jinkou": 122742.0, "jinkou_desc": null, "otoko": 60274.0, "otoko_desc": null, "onna": 62468.0, "onna_desc": null}, {"year_id": 2015100000.0, "year": "2015年度", "area_id": 13215.0, "area": "東京都 国立市", "desc": null, "jinkou": 73655.0, "jinkou_desc": null, "otoko": 35970.0, "otoko_desc": null, "onna": 37685.0, "onna_desc": null}, {"year_id": 2015100000.0, "year": "2015年度", "area_id": 13218.0, "area": "東京都 福生市", "desc": null, "jinkou": 58395.0, "jinkou_desc": null, "otoko": 29238.0, "otoko_desc": null, "onna": 29157.0, "onna_desc": null}, {"year_id": 2015100000.0, "year": "2015年度", "area_id": 13219.0, "area": "東京都 狛江市", "desc": null, "jinkou": 80249.0, "jinkou_desc": null, "otoko": 39206.0, "otoko_desc": null, "onna": 41043.0, "onna_desc": null}, {"year_id": 2015100000.0, "year": "2015年度", "area_id": 13220.0, "area": "東京都 東大和市", "desc": null, "jinkou": 85157.0, "jinkou_desc": null, "otoko": 41820.0, "otoko_desc": null, "onna": 43337.0, "onna_desc": null}, {"year_id": 2015100000.0, "year": "2015年度", "area_id": 13221.0, "area": "東京都 清瀬市", "desc": null, "jinkou": 74864.0, "jinkou_desc": null, "otoko": 35968.0, "otoko_desc": null, "onna": 38896.0, "onna_desc": null}, {"year_id": 2015100000.0, "year": "2015年度", "area_id": 13222.0, "area": "東京都 東久留米市", "desc": null, "jinkou": 116632.0, "jinkou_desc": null, "otoko": 56738.0, "otoko_desc": null, "onna": 59894.0, "onna_desc": null}, {"year_id": 2015100000.0, "year": "2015年度", "area_id": 13223.0, "area": "東京都 武蔵村山市", "desc": null, "jinkou": 71229.0, "jinkou_desc": null, "otoko": 35556.0, "otoko_desc": null, "onna": 35673.0, "onna_desc": null}, {"year_id": 2015100000.0, "year": "2015年度", "area_id": 13224.0, "area": "東京都 多摩市", "desc": null, "jinkou": 146631.0, "jinkou_desc": null, "otoko": 71762.0, "otoko_desc": null, "onna": 74869.0, "onna_desc": null}, {"year_id": 2015100000.0, "year": "2015年度", "area_id": 13225.0, "area": "東京都 稲城市", "desc": null, "jinkou": 87636.0, "jinkou_desc": null, "otoko": 44041.0, "otoko_desc": null, "onna": 43595.0, "onna_desc": null}, {"year_id": 2015100000.0, "year": "2015年度", "area_id": 13227.0, "area": "東京都 羽村市", "desc": null, "jinkou": 55833.0, "jinkou_desc": null, "otoko": 28451.0, "otoko_desc": null, "onna": 27382.0, "onna_desc": null}, {"year_id": 2015100000.0, "year": "2015年度", "area_id": 13228.0, "area": "東京都 あきる野市", "desc": null, "jinkou": 80954.0, "jinkou_desc": null, "otoko": 40218.0, "otoko_desc": null, "onna": 40736.0, "onna_desc": null}, {"year_id": 2015100000.0, "year": "2015年度", "area_id": 13229.0, "area": "東京都 西東京市", "desc": null, "jinkou": 200012.0, "jinkou_desc": null, "otoko": 97830.0, "otoko_desc": null, "onna": 102182.0, "onna_desc": null}, {"year_id": 2015100000.0, "year": "2015年度", "area_id": 13303.0, "area": "東京都 瑞穂町", "desc": null, "jinkou": 33445.0, "jinkou_desc": null, "otoko": 16951.0, "otoko_desc": null, "onna": 16494.0, "onna_desc": null}, {"year_id": 2015100000.0, "year": "2015年度", "area_id": 13305.0, "area": "東京都 日の出町", "desc": null, "jinkou": 17446.0, "jinkou_desc": null, "otoko": 8485.0, "otoko_desc": null, "onna": 8961.0, "onna_desc": null}, {"year_id": 2015100000.0, "year": "2015年度", "area_id": 13307.0, "area": "東京都 檜原村", "desc": null, "jinkou": 2209.0, "jinkou_desc": null, "otoko": 1081.0, "otoko_desc": null, "onna": 1128.0, "onna_desc": null}, {"year_id": 2015100000.0, "year": "2015年度", "area_id": 13308.0, "area": "東京都 奥多摩町", "desc": null, "jinkou": 5234.0, "jinkou_desc": null, "otoko": 2579.0, "otoko_desc": null, "onna": 2655.0, "onna_desc": null}, {"year_id": 2015100000.0, "year": "2015年度", "area_id": 13361.0, "area": "東京都 大島町", "desc": null, "jinkou": 7884.0, "jinkou_desc": null, "otoko": 4031.0, "otoko_desc": null, "onna": 3853.0, "onna_desc": null}, {"year_id": 2015100000.0, "year": "2015年度", "area_id": 13362.0, "area": "東京都 利島村", "desc": null, "jinkou": 337.0, "jinkou_desc": null, "otoko": 191.0, "otoko_desc": null, "onna": 146.0, "onna_desc": null}, {"year_id": 2015100000.0, "year": "2015年度", "area_id": 13363.0, "area": "東京都 新島村", "desc": null, "jinkou": 2749.0, "jinkou_desc": null, "otoko": 1344.0, "otoko_desc": null, "onna": 1405.0, "onna_desc": null}, {"year_id": 2015100000.0, "year": "2015年度", "area_id": 13364.0, "area": "東京都 神津島村", "desc": null, "jinkou": 1891.0, "jinkou_desc": null, "otoko": 969.0, "otoko_desc": null, "onna": 922.0, "onna_desc": null}, {"year_id": 2015100000.0, "year": "2015年度", "area_id": 13381.0, "area": "東京都 三宅村", "desc": null, "jinkou": 2482.0, "jinkou_desc": null, "otoko": 1350.0, "otoko_desc": null, "onna": 1132.0, "onna_desc": null}, {"year_id": 2015100000.0, "year": "2015年度", "area_id": 13382.0, "area": "東京都 御蔵島村", "desc": null, "jinkou": 335.0, "jinkou_desc": null, "otoko": 189.0, "otoko_desc": null, "onna": 146.0, "onna_desc": null}, {"year_id": 2015100000.0, "year": "2015年度", "area_id": 13401.0, "area": "東京都 八丈町", "desc": null, "jinkou": 7613.0, "jinkou_desc": null, "otoko": 3785.0, "otoko_desc": null, "onna": 3828.0, "onna_desc": null}, {"year_id": 2015100000.0, "year": "2015年度", "area_id": 13402.0, "area": "東京都 青ヶ島村", "desc": null, "jinkou": 178.0, "jinkou_desc": null, "otoko": 107.0, "otoko_desc": null, "onna": 71.0, "onna_desc": null}, {"year_id": 2015100000.0, "year": "2015年度", "area_id": 13421.0, "area": "東京都 小笠原村", "desc": null, "jinkou": 3022.0, "jinkou_desc": null, "otoko": 1893.0, "otoko_desc": null, "onna": 1129.0, "onna_desc": null}]